{
	"webSecurity": false,
	"cookiesFile": "data/cookies",
	"localStoragePath": "data/localStorage",
	"localStorageQuota": 65536,
	"localToRemoteUrlAccess": true,
	"diskCache": true,
	"maxDiskCacheSize": 16384,

	"browserViewport": {
		"width": 1600,
		"height": 1200
	},
    "mutedLogTypes": ["EVENT", "CONSOLE", "PAGE", "ScreenshotService"],
	"defaultZoom": 17,
	"screenshotService": true,
	"screenshotServicePort": 9001,
	"scannerService": true,
	"scannerServicePort": 9002,
	"pauseAfterSectorScan": 1,
	"pauseAfterFieldScan": 10,
	"pauseBeforeRescan": 300,
	"username": "john.doe@gmail.com",
	"password": "cheeseburger",
	"scheduleDataFile": "data/schedule.json",
	"schedulerHtmlFile": "assets/scheduler.html"
}